ml_hadoop_experiment/__init__.py
ml_hadoop_experiment/common/__init__.py
ml_hadoop_experiment/common/paths.py
ml_hadoop_experiment/common/spark_inference.py
ml_hadoop_experiment/pytorch/__init__.py
ml_hadoop_experiment/pytorch/spark_inference.py
ml_hadoop_experiment/pytorch/fixtures/__init__.py
ml_hadoop_experiment/pytorch/fixtures/test_models.py
ml_hadoop_experiment/sklearn/__init__.py
ml_hadoop_experiment/sklearn/spark_inference.py
ml_hadoop_experiment/tensorflow/__init__.py
ml_hadoop_experiment/tensorflow/constant.py
ml_hadoop_experiment/tensorflow/dataframe_prediction_helper.py
ml_hadoop_experiment/tensorflow/dataframe_to_tf_helper.py
ml_hadoop_experiment/tensorflow/evaluator_conf_helper.py
ml_hadoop_experiment/tensorflow/events.py
ml_hadoop_experiment/tensorflow/keras_bootstrap_helper.py
ml_hadoop_experiment/tensorflow/logging.conf.py
ml_hadoop_experiment/tensorflow/numpy_to_sparse_tensors.py
ml_hadoop_experiment/tensorflow/pandas_to_tensors.py
ml_hadoop_experiment/tensorflow/predictor.py
ml_hadoop_experiment/tensorflow/sampling.py
ml_hadoop_experiment/tensorflow/serving_input_receiver_fn_makers.py
ml_hadoop_experiment/tensorflow/tfrecords.py
ml_hadoop_experiment/tensorflow/vocabulary.py
ml_hadoop_experiment-0.0.5.dist-info/LICENSE
ml_hadoop_experiment-0.0.5.dist-info/METADATA
ml_hadoop_experiment-0.0.5.dist-info/WHEEL
ml_hadoop_experiment-0.0.5.dist-info/top_level.txt
ml_hadoop_experiment-0.0.5.dist-info/RECORD
